simoc_abm/.DS_Store
simoc_abm/__init__.py
simoc_abm/agent_model.py
simoc_abm/util.py
simoc_abm/viz.py
simoc_abm/agents/__init__.py
simoc_abm/agents/atmosphere_equalizer.py
simoc_abm/agents/base.py
simoc_abm/agents/concrete.py
simoc_abm/agents/lamp.py
simoc_abm/agents/plant.py
simoc_abm/agents/sun.py
simoc_abm/data_files/__init__.py
simoc_abm/data_files/agent_desc.json
simoc_abm/data_files/config_1h.json
simoc_abm/data_files/config_1hg_sam.json
simoc_abm/data_files/config_1hrad.json
simoc_abm/data_files/config_4h.json
simoc_abm/data_files/config_4hg.json
simoc_abm/data_files/config_b2_mission1a.json
simoc_abm/data_files/config_b2_mission1b.json
simoc_abm/data_files/config_b2_mission2.json
simoc_abm/data_files/currency_desc.json
simoc_abm-1.1.2.dist-info/METADATA
simoc_abm-1.1.2.dist-info/WHEEL
simoc_abm-1.1.2.dist-info/licenses/LICENSE
simoc_abm-1.1.2.dist-info/RECORD
