Metadata-Version: 2.1
Name: simoc_abm
Version: 1.1.2
Summary: Agent Based Modelling for Ecosystems
Project-URL: Homepage, https://github.com/overthesun/simoc-abm
Project-URL: Bug Tracker, https://github.com/overthesun/simoc-abm/issues
Project-URL: Documentation, https://simoc-abm.readthedocs.org
Author-email: Grant Hawkins <granthawkins88@gmail.com>
License-File: LICENSE
Classifier: License :: OSI Approved :: GNU General Public License v3 (GPLv3)
Classifier: Operating System :: OS Independent
Classifier: Programming Language :: Python :: 3
Requires-Python: >=3.9
